LICENSE.txt
MANIFEST.in
README.md
setup.py
bin/concoct
c-concoct/vbgmmmodule.c
c-concoct/vbgmmmodule.h
concoct/__init__.py
concoct/cluster.py
concoct/input.py
concoct/output.py
concoct/parser.py
concoct/transform.py
concoct.egg-info/PKG-INFO
concoct.egg-info/SOURCES.txt
concoct.egg-info/dependency_links.txt
concoct.egg-info/entry_points.txt
concoct.egg-info/not-zip-safe
concoct.egg-info/requires.txt
concoct.egg-info/top_level.txt