Metadata-Version: 1.0
Name: concoct
Version: 0.3.1
Summary: Clustering cONtigs with COverage and ComposiTion
Home-page: https://github.com/BinPro/CONCOCT
Author: Johannes Alneberg
Author-email: johannes.alneberg@scilifelab.se
License: FreeBSD
Keywords: Python Scilifelab Metagenomics Binning Clustering Contig
Platform: UNKNOWN
